{"Usage_title": 0, "Usage_extraction": 0, "generatedTitle": "longest running tv shows in india", "extractFactDictList": [{"question": "What is the nationality of the Indian population?", "phrase": "Indian", "sentence": "Television has been an integral part of Indian households for decades."}, {"question": "How long has television been an integral part of Indian households?", "phrase": "decades", "sentence": "Television has been an integral part of Indian households for decades."}, {"question": "In what country are the longest running TV shows?", "phrase": "India", "sentence": "In this article, we will take a look at the longest running TV shows in India."}, {"question": "What culture have these shows become a part of?", "phrase": "Indian", "sentence": "These shows have entertained generations of viewers and have become a part of Indian pop culture."}, {"question": "Where are the longest running TV shows in India?", "phrase": "India", "sentence": "Let's dive in and explore the list of longest running TV shows in India."}]}