[{"question": "What is the name of the popular television series that has been entertaining audiences since its inception?", "phrase": "Hawaii Five-O", "predAns": "Masi Oka", "predScore": 0.965487003326416, "MatchScore": {"entailment": 0.051009442657232285, "neutral": 0.11297747492790222, "contradiction": 0.8360130786895752}, "oriSent": "Hawaii Five-O is a popular television series that has been entertaining audiences since The show follows a team of detectives tasked with solving crimes in the beautiful state of Hawaii.", "process": "se", "properAnsIDList": 1}, {"question": "What state is Hawaii Five-O set in?", "phrase": "Hawaii", "predAns": "Masi Oka", "predScore": 0.9698057174682617, "MatchScore": {"entailment": 0.1136951595544815, "neutral": 0.3098607659339905, "contradiction": 0.5764440894126892}, "oriSent": "Hawaii Five-O is a popular television series that has been entertaining audiences since The show follows a team of detectives tasked with solving crimes in the beautiful state of Hawaii.", "process": "se", "properAnsIDList": 4}, {"question": "How many of the medical examiners on American Idol are there?", "phrase": "One", "predAns": "Masi Oka", "predScore": 0.9565702676773071, "MatchScore": {"entailment": 0.29104751348495483, "neutral": 0.17394882440567017, "contradiction": 0.535003662109375}, "oriSent": "One of the key characters on the show is the medical examiner, who plays a crucial role in helping the detectives solve crimes.", "process": "se", "properAnsIDList": 3}, {"question": "What state plays the medical examiner on the show?", "phrase": "Hawaii", "predAns": "Masi Oka", "predScore": 0.8919047117233276, "MatchScore": {"entailment": 0.1136951595544815, "neutral": 0.3098607659339905, "contradiction": 0.5764440894126892}, "oriSent": "But who plays the medical examiner on Hawaii Five-O?", "process": "se", "properAnsIDList": 1}, {"question": "On what show is Dr. Max Bergman a medical examiner?", "phrase": "Hawaii Five-O", "predAns": "Masi Oka", "predScore": 0.9814239740371704, "MatchScore": {"entailment": 0.051009442657232285, "neutral": 0.11297747492790222, "contradiction": 0.8360130786895752}, "oriSent": "The character of the medical examiner on Hawaii Five-O is named Dr. Max Bergman, and he is played by actor Daniel Dae Kim.", "process": "se", "properAnsIDList": 6}, {"question": "What is the name of the medical examiner on Hawaii Five-O?", "phrase": "Max Bergman", "predAns": "Dr. Max Bergman", "predScore": 0.664122998714447, "MatchScore": {"entailment": 0.9181397557258606, "neutral": 0.05891067162156105, "contradiction": 0.02294950932264328}, "oriSent": "The character of the medical examiner on Hawaii Five-O is named Dr. Max Bergman, and he is played by actor Daniel Dae Kim.", "process": "se", "properAnsIDList": 1}, {"question": "Who plays Dr. Max Bergman?", "phrase": "Daniel Dae Kim", "predAns": "Masi Oka", "predScore": 0.9912353754043579, "MatchScore": {"entailment": 0.019899552688002586, "neutral": 0.0297689288854599, "contradiction": 0.9503315687179565}, "oriSent": "The character of the medical examiner on Hawaii Five-O is named Dr. Max Bergman, and he is played by actor Daniel Dae Kim.", "process": "se", "properAnsIDList": 8}, {"question": "What is the name of the Korean-American actor who was raised in the United States?", "phrase": "Daniel Dae Kim", "predAns": "Masi Oka", "predScore": 0.8932778239250183, "MatchScore": {"entailment": 0.019899552688002586, "neutral": 0.0297689288854599, "contradiction": 0.9503315687179565}, "oriSent": "Daniel Dae Kim is a Korean-American actor who was born in South Korea and raised in the United States.", "process": "se", "properAnsIDList": 6}, {"question": "What ethnicity is Kim?", "phrase": "Korean-American", "predAns": "Hawaiian", "predScore": 0.8046117424964905, "MatchScore": {"entailment": 0.03592082858085632, "neutral": 0.5111441016197205, "contradiction": 0.45293501019477844}, "oriSent": "Daniel Dae Kim is a Korean-American actor who was born in South Korea and raised in the United States.", "process": "se", "properAnsIDList": 1}, {"question": "Where was Kim born?", "phrase": "South Korea", "predAns": "South Korea", "predScore": 0.8879026770591736, "MatchScore": {"entailment": 0.943165123462677, "neutral": 0.04582374170422554, "contradiction": 0.011011059395968914}, "oriSent": "Daniel Dae Kim is a Korean-American actor who was born in South Korea and raised in the United States.", "process": "se", "properAnsIDList": 6}, {"question": "Where was Kim raised?", "phrase": "the United States", "predAns": "Hawaii", "predScore": 0.7306084036827087, "MatchScore": {"entailment": 0.6636733412742615, "neutral": 0.3014684319496155, "contradiction": 0.03485826030373573}, "oriSent": "Daniel Dae Kim is a Korean-American actor who was born in South Korea and raised in the United States.", "process": "se", "properAnsIDList": 3}, {"question": "What role did Kim play on Hawaii Five-O?", "phrase": "Bergman", "predAns": "Dr. Noelani Cunha", "predScore": 0.5512056350708008, "MatchScore": {"entailment": 0.047952160239219666, "neutral": 0.037248287349939346, "contradiction": 0.9147995114326477}, "oriSent": "Before landing the role of Dr. Bergman on Hawaii Five-O, Kim had appeared in a number of other television shows, including Lost and In addition to his work on Hawaii Five-O, Kim has also appeared in several films, including The Jackal and The Darjeeling Limited.", "process": "se", "properAnsIDList": 1}, {"question": "What television show did Kim appear on?", "phrase": "Hawaii Five-O", "predAns": "Hawaii Five-0", "predScore": 0.6131349802017212, "MatchScore": {"entailment": 0.02923639863729477, "neutral": 0.024187324568629265, "contradiction": 0.9465763568878174}, "oriSent": "Before landing the role of Dr. Bergman on Hawaii Five-O, Kim had appeared in a number of other television shows, including Lost and In addition to his work on Hawaii Five-O, Kim has also appeared in several films, including The Jackal and The Darjeeling Limited.", "process": "se", "properAnsIDList": 3}, {"question": "Who has appeared in The Jackal and The Darjeeling Limited?", "phrase": "Kim", "predAns": "Masi Oka", "predScore": 0.9528045058250427, "MatchScore": {"entailment": 0.06857696175575256, "neutral": 0.057658225297927856, "contradiction": 0.8737648129463196}, "oriSent": "Before landing the role of Dr. Bergman on Hawaii Five-O, Kim had appeared in a number of other television shows, including Lost and In addition to his work on Hawaii Five-O, Kim has also appeared in several films, including The Jackal and The Darjeeling Limited.", "process": "se", "properAnsIDList": 1}, {"question": "What television show did Kim appear in?", "phrase": "Lost", "predAns": "Hawaii Five-0", "predScore": 0.7584031224250793, "MatchScore": {"entailment": 0.034583792090415955, "neutral": 0.03632410243153572, "contradiction": 0.9290921092033386}, "oriSent": "Before landing the role of Dr. Bergman on Hawaii Five-O, Kim had appeared in a number of other television shows, including Lost and In addition to his work on Hawaii Five-O, Kim has also appeared in several films, including The Jackal and The Darjeeling Limited.", "process": "se", "properAnsIDList": 0}, {"question": "What film did Kim appear in?", "phrase": "The Jackal", "predAns": "Hawaii Five-0", "predScore": 0.6834030747413635, "MatchScore": {"entailment": 0.030679240822792053, "neutral": 0.041686613112688065, "contradiction": 0.927634060382843}, "oriSent": "Before landing the role of Dr. Bergman on Hawaii Five-O, Kim had appeared in a number of other television shows, including Lost and In addition to his work on Hawaii Five-O, Kim has also appeared in several films, including The Jackal and The Darjeeling Limited.", "process": "se", "properAnsIDList": 6}, {"question": "Along with The Jackal, what film has Kim appeared in?", "phrase": "The Darjeeling Limited", "predAns": "Blast Blast", "predScore": 0.8640052676200867, "MatchScore": {"entailment": 0.04656851291656494, "neutral": 0.290133535861969, "contradiction": 0.6632978916168213}, "oriSent": "Before landing the role of Dr. Bergman on Hawaii Five-O, Kim had appeared in a number of other television shows, including Lost and In addition to his work on Hawaii Five-O, Kim has also appeared in several films, including The Jackal and The Darjeeling Limited.", "process": "se", "properAnsIDList": 2}, {"question": "Who played Dr. Bergman on Hawaii Five-O?", "phrase": "Kim", "predAns": "Masi Oka", "predScore": 0.9729533195495605, "MatchScore": {"entailment": 0.06857696175575256, "neutral": 0.057658225297927856, "contradiction": 0.8737648129463196}, "oriSent": "Kim's portrayal of Dr. Bergman on Hawaii Five-O has been well-received by audiences and critics alike, and he has become a fan favorite on the show.", "process": "se", "properAnsIDList": 8}, {"question": "What character has become a fan favorite on Hawaii Five-O?", "phrase": "Bergman", "predAns": "Max Bergman", "predScore": 0.9018235802650452, "MatchScore": {"entailment": 0.8955099582672119, "neutral": 0.07643145322799683, "contradiction": 0.02805856242775917}, "oriSent": "Kim's portrayal of Dr. Bergman on Hawaii Five-O has been well-received by audiences and critics alike, and he has become a fan favorite on the show.", "process": "se", "properAnsIDList": 1}, {"question": "What show did Kim play Dr. Bergman on?", "phrase": "Hawaii Five-O", "predAns": "CBS", "predScore": 0.44909772276878357, "MatchScore": {"entailment": 0.05843937769532204, "neutral": 0.9249576926231384, "contradiction": 0.016602909192442894}, "oriSent": "Kim's portrayal of Dr. Bergman on Hawaii Five-O has been well-received by audiences and critics alike, and he has become a fan favorite on the show.", "process": "se", "properAnsIDList": 6}, {"question": "On what show is Daniel Dae Kim the medical examiner?", "phrase": "Hawaii Five-O", "predAns": "Five-0", "predScore": 0.876374363899231, "MatchScore": {"entailment": 0.09656111150979996, "neutral": 0.4154703617095947, "contradiction": 0.4879685044288635}, "oriSent": "In conclusion, the medical examiner on Hawaii Five-O is played by actor Daniel Dae Kim.", "process": "se", "properAnsIDList": 8}, {"question": "Who plays the medical examiner on Hawaii Five-O?", "phrase": "Daniel Dae Kim", "predAns": "Noelani Cunha", "predScore": 0.9526045918464661, "MatchScore": {"entailment": 0.008643344044685364, "neutral": 0.007076721638441086, "contradiction": 0.9842798709869385}, "oriSent": "In conclusion, the medical examiner on Hawaii Five-O is played by actor Daniel Dae Kim.", "process": "se", "properAnsIDList": 3}, {"question": "Who is the actor who has brought Dr. Bergman to life on American Idol?", "phrase": "Kim", "predAns": "Masi Oka", "predScore": 0.9695920944213867, "MatchScore": {"entailment": 0.06857696175575256, "neutral": 0.057658225297927856, "contradiction": 0.8737648129463196}, "oriSent": "Kim is a talented actor who has brought the character of Dr. Bergman to life on the show, and his portrayal has been well-received by audiences.", "process": "se", "properAnsIDList": 2}, {"question": "What character has Kim played?", "phrase": "Bergman", "predAns": "Dr", "predScore": 0.5827879309654236, "MatchScore": {"entailment": 0.13047467172145844, "neutral": 0.3967529535293579, "contradiction": 0.47277241945266724}, "oriSent": "Kim is a talented actor who has brought the character of Dr. Bergman to life on the show, and his portrayal has been well-received by audiences.", "process": "se", "properAnsIDList": 0}, {"question": "In what country is the medical examiner on the show?", "phrase": "Hawaii", "predAns": "Balmilero", "predScore": 0.8453423380851746, "MatchScore": {"entailment": 0.06332433968782425, "neutral": 0.09539198130369186, "contradiction": 0.8412836194038391}, "oriSent": "We hope this introduction has provided you with some useful and verifiable facts about the actor who plays the medical examiner on Hawaii Five-O.", "process": "se", "properAnsIDList": 6}]