[{"question": "What is the name of the classical dance form of Andhra Pradesh?", "phrase": "Kuchipudi", "predAns": "Bhagawatmela", "predScore": 0.8125898241996765, "MatchScore": {"entailment": 0.0969286635518074, "neutral": 0.10852886736392975, "contradiction": 0.7945424914360046}, "oriSent": "Kuchipudi is a classical dance form of Andhra Pradesh, a state located in the southeastern part of India.", "process": "se", "properAnsIDList": 8}, {"question": "What state is Kuchipudi from?", "phrase": "Andhra Pradesh", "predAns": "Andhra Pradesh", "predScore": 0.9841775894165039, "MatchScore": {"entailment": 0.954340934753418, "neutral": 0.03837916627526283, "contradiction": 0.007279898039996624}, "oriSent": "Kuchipudi is a classical dance form of Andhra Pradesh, a state located in the southeastern part of India.", "process": "se", "properAnsIDList": 8}, {"question": "Where is Andhra Pradesh located?", "phrase": "India", "predAns": "Krishna district", "predScore": 0.7830896377563477, "MatchScore": {"entailment": 0.12314275652170181, "neutral": 0.8397859930992126, "contradiction": 0.03707122430205345}, "oriSent": "Kuchipudi is a classical dance form of Andhra Pradesh, a state located in the southeastern part of India.", "process": "se", "properAnsIDList": 7}, {"question": "How many traditional dance forms are there in India?", "phrase": "eight", "predAns": "eight", "predScore": 0.7521095871925354, "MatchScore": {"entailment": 0.9469560980796814, "neutral": 0.04036330431699753, "contradiction": 0.012680619023740292}, "oriSent": "It is one of the eight traditional dance forms of India and is known for its intricate footwork, graceful movements, and expressive gestures.", "process": "se", "properAnsIDList": 4}, {"question": "What country is the dance of the footwork?", "phrase": "India", "predAns": "India", "predScore": 0.9676253199577332, "MatchScore": {"entailment": 0.8968167901039124, "neutral": 0.08479239791631699, "contradiction": 0.01839076541364193}, "oriSent": "It is one of the eight traditional dance forms of India and is known for its intricate footwork, graceful movements, and expressive gestures.", "process": "se", "properAnsIDList": 4}, {"question": "What dance originated in the 10th century?", "phrase": "Kuchipudi", "predAns": "tarangam", "predScore": 0.7130589485168457, "MatchScore": {"entailment": 0.1442481428384781, "neutral": 0.17724627256393433, "contradiction": 0.6785055994987488}, "oriSent": "Kuchipudi is believed to have originated in the 10th century and has been passed down through generations of dancers in Andhra Pradesh.", "process": "se", "properAnsIDList": 5}, {"question": "When was Kuchipudi believed to have originated?", "phrase": "the 10th century", "predAns": "3rd century BCE", "predScore": 0.8419928550720215, "MatchScore": {"entailment": 0.001729731447994709, "neutral": 0.013867979869246483, "contradiction": 0.9844022989273071}, "oriSent": "Kuchipudi is believed to have originated in the 10th century and has been passed down through generations of dancers in Andhra Pradesh.", "process": "se", "properAnsIDList": 1}, {"question": "Where is Kuchipudi believed to have originated?", "phrase": "Andhra Pradesh", "predAns": "Manipur", "predScore": 0.9641709327697754, "MatchScore": {"entailment": 0.031763218343257904, "neutral": 0.04187017306685448, "contradiction": 0.9263665676116943}, "oriSent": "Kuchipudi is believed to have originated in the 10th century and has been passed down through generations of dancers in Andhra Pradesh.", "process": "se", "properAnsIDList": 1}, {"question": "What is the name of the city that is the center of the world?", "phrase": "Kuchipudi", "predAns": "<unanswerable>", "predScore": 0, "MatchScore": {"entailment": 0.06510166078805923, "neutral": 0.7701919674873352, "contradiction": 0.16470637917518616}, "oriSent": "History of Kuchipudi:", "process": "se", "properAnsIDList": 0}, {"question": "What is the name of the village that is believed to have originated in the 10th century?", "phrase": "Kuchipudi", "predAns": "kuchelapuram", "predScore": 0.9044586420059204, "MatchScore": {"entailment": 0.37661153078079224, "neutral": 0.17360882461071014, "contradiction": 0.4497796893119812}, "oriSent": "Kuchipudi is believed to have originated in the 10th century in the village of Kuchelapuram in Andhra Pradesh.", "process": "se", "properAnsIDList": 8}, {"question": "When is Kuchipudi believed to have originated?", "phrase": "the 10th century", "predAns": "2nd century BCE", "predScore": 0.7773037552833557, "MatchScore": {"entailment": 0.002069238107651472, "neutral": 0.01566208340227604, "contradiction": 0.9822686910629272}, "oriSent": "Kuchipudi is believed to have originated in the 10th century in the village of Kuchelapuram in Andhra Pradesh.", "process": "se", "properAnsIDList": 7}, {"question": "Where is Kuchipudi believed to have originated?", "phrase": "Kuchelapuram", "predAns": "Manipur", "predScore": 0.9641709327697754, "MatchScore": {"entailment": 0.08982635289430618, "neutral": 0.08078470826148987, "contradiction": 0.8293889164924622}, "oriSent": "Kuchipudi is believed to have originated in the 10th century in the village of Kuchelapuram in Andhra Pradesh.", "process": "se", "properAnsIDList": 1}, {"question": "Where is Kuchipudi believed to have originated?", "phrase": "Andhra Pradesh", "predAns": "Manipur", "predScore": 0.9641709327697754, "MatchScore": {"entailment": 0.031763218343257904, "neutral": 0.04187017306685448, "contradiction": 0.9263665676116943}, "oriSent": "Kuchipudi is believed to have originated in the 10th century in the village of Kuchelapuram in Andhra Pradesh.", "process": "se", "properAnsIDList": 1}, {"question": "Who created the dance form?", "phrase": "Veda Vyasa", "predAns": "Siddendra yogi", "predScore": 0.9498447179794312, "MatchScore": {"entailment": 0.059944428503513336, "neutral": 0.09089284390211105, "contradiction": 0.849162757396698}, "oriSent": "The dance form is named after this village and is said to have been created by the sage Veda Vyasa.", "process": "se", "properAnsIDList": 6}, {"question": "Who was instrumental in developing the dance form?", "phrase": "Veda Vyasa", "predAns": "Raja and Radha Reddy", "predScore": 0.598722517490387, "MatchScore": {"entailment": 0.042447011917829514, "neutral": 0.04455464705824852, "contradiction": 0.912998378276825}, "oriSent": "According to legend, Veda Vyasa was instrumental in developing the dance form as a way to express the emotions and stories of the Hindu epics, such as the Ramayana and the Mahabharata.", "process": "se", "properAnsIDList": 4}, {"question": "What type of epics did the Ramayana and Mahabharata belong to?", "phrase": "Hindu", "predAns": "Hindu", "predScore": 0.8153611421585083, "MatchScore": {"entailment": 0.9224092960357666, "neutral": 0.05716637149453163, "contradiction": 0.020424379035830498}, "oriSent": "According to legend, Veda Vyasa was instrumental in developing the dance form as a way to express the emotions and stories of the Hindu epics, such as the Ramayana and the Mahabharata.", "process": "se", "properAnsIDList": 4}, {"question": "Along with the Mahabharata, what Hindu epic is danced in?", "phrase": "Ramayana", "predAns": "Natya Shastra", "predScore": 0.9580581188201904, "MatchScore": {"entailment": 0.04822028800845146, "neutral": 0.06372030824422836, "contradiction": 0.8880593776702881}, "oriSent": "According to legend, Veda Vyasa was instrumental in developing the dance form as a way to express the emotions and stories of the Hindu epics, such as the Ramayana and the Mahabharata.", "process": "se", "properAnsIDList": 0}, {"question": "Along with the Ramayana, what Hindu epic is dance a part of?", "phrase": "Mahabharata", "predAns": "Mahabharata", "predScore": 0.9884079694747925, "MatchScore": {"entailment": 0.9289847612380981, "neutral": 0.05491838604211807, "contradiction": 0.0160968080163002}, "oriSent": "According to legend, Veda Vyasa was instrumental in developing the dance form as a way to express the emotions and stories of the Hindu epics, such as the Ramayana and the Mahabharata.", "process": "se", "properAnsIDList": 6}, {"question": "What dance form evolved over time?", "phrase": "Kuchipudi", "predAns": "Naatyamela & Natvamela", "predScore": 0.7184917330741882, "MatchScore": {"entailment": 0.10474808514118195, "neutral": 0.13347989320755005, "contradiction": 0.7617720365524292}, "oriSent": "Over time, Kuchipudi evolved into a distinct dance form with its own unique style and techniques.", "process": "se", "properAnsIDList": 7}, {"question": "What is the name of the software that is used to make the software?", "phrase": "Kuchipudi", "predAns": "Autodesk Maya", "predScore": 0.3658267557621002, "MatchScore": {"entailment": 0.14747510850429535, "neutral": 0.2351493090391159, "contradiction": 0.6173755526542664}, "oriSent": "Features of Kuchipudi:", "process": "se", "properAnsIDList": 5}, {"question": "What is characterized by its intricate footwork, graceful movements, and expressive gestures?", "phrase": "Kuchipudi", "predAns": "jathis", "predScore": 0.8433510661125183, "MatchScore": {"entailment": 0.04999115690588951, "neutral": 0.05891994759440422, "contradiction": 0.8910888433456421}, "oriSent": "Kuchipudi is characterized by its intricate footwork, graceful movements, and expressive gestures.", "process": "se", "properAnsIDList": 0}, {"question": "What language is the traditional dance form performed to?", "phrase": "Telugu", "predAns": "Indian", "predScore": 0.9756489396095276, "MatchScore": {"entailment": 0.021204721182584763, "neutral": 0.05646189674735069, "contradiction": 0.9223333597183228}, "oriSent": "The dance form is performed to traditional Telugu music, which is played on instruments such as the veena, flute, and drums.", "process": "se", "properAnsIDList": 0}, {"question": "What state's traditional attire is worn by dancers?", "phrase": "Andhra Pradesh", "predAns": "Andhra Pradesh", "predScore": 0.9528223872184753, "MatchScore": {"entailment": 0.954340934753418, "neutral": 0.03837916627526283, "contradiction": 0.007279898039996624}, "oriSent": "The dancers wear traditional Andhra Pradesh attire, which includes a long skirt and a blouse with intricate embroidery.", "process": "se", "properAnsIDList": 4}, {"question": "What is the name of the film that emphasizes storytelling and expression?", "phrase": "Kuchipudi", "predAns": "Krishna", "predScore": 0.8907734751701355, "MatchScore": {"entailment": 0.10246935486793518, "neutral": 0.139115571975708, "contradiction": 0.7584150433540344}, "oriSent": "Kuchipudi is known for its emphasis on storytelling and expression.", "process": "se", "properAnsIDList": 0}, {"question": "What is the significance of Kuchipudi?", "phrase": "Kuchipudi", "predAns": "one of the classical styles of Indian dance", "predScore": 0.6240932941436768, "MatchScore": {"entailment": 0.15830901265144348, "neutral": 0.7679613828659058, "contradiction": 0.07372958213090897}, "oriSent": "Significance of Kuchipudi:", "process": "se", "properAnsIDList": 5}, {"question": "What is one of the most popular dance forms in India?", "phrase": "Kuchipudi", "predAns": "Kathak", "predScore": 0.581349790096283, "MatchScore": {"entailment": 0.1607438027858734, "neutral": 0.19155457615852356, "contradiction": 0.647701621055603}, "oriSent": "Kuchipudi is an important part of Andhra Pradesh's cultural heritage and is considered to be one of the most popular dance forms of India.", "process": "se", "properAnsIDList": 4}, {"question": "What state has a large cultural heritage?", "phrase": "Andhra Pradesh's", "predAns": "Andhra Pradesh", "predScore": 0.9767187237739563, "MatchScore": {"entailment": 0.5693290829658508, "neutral": 0.3456764221191406, "contradiction": 0.08499450981616974}, "oriSent": "Kuchipudi is an important part of Andhra Pradesh's cultural heritage and is considered to be one of the most popular dance forms of India.", "process": "se", "properAnsIDList": 1}, {"question": "Kuchipudi is considered to be one of the most popular dance forms in what country?", "phrase": "India", "predAns": "India", "predScore": 0.41090816259384155, "MatchScore": {"entailment": 0.8968167901039124, "neutral": 0.08479239791631699, "contradiction": 0.01839076541364193}, "oriSent": "Kuchipudi is an important part of Andhra Pradesh's cultural heritage and is considered to be one of the most popular dance forms of India.", "process": "se", "properAnsIDList": 3}]