[{"question": "What university did a student at admitted to hanging a rope from a tree?", "phrase": "Duke University", "predAns": "made of rope", "predScore": 0.8080856204032898, "MatchScore": {"entailment": 0.021962972357869148, "neutral": 0.7847486138343811, "contradiction": 0.1932884156703949}, "oriSent": "A student at Duke University admitted to hanging a noose made of rope from a tree near a student union.", "process": "document", "properAnsIDList": "document"}, {"question": "What university is the student no longer at?", "phrase": "Duke University", "predAns": "made of rope", "predScore": 0.7029698491096497, "MatchScore": {"entailment": 0.021962972357869148, "neutral": 0.7847486138343811, "contradiction": 0.1932884156703949}, "oriSent": "The student is no longer on the Duke University campus and will face a disciplinary review.", "process": "document", "properAnsIDList": "document"}]