[{"question": "What is the name of the song composed by Bankim Chandra Chattopadhyay?", "phrase": "Vande Mataram", "predAns": "Zubeen Garg", "predScore": 0.9617975950241089, "MatchScore": {"entailment": 0.15844526886940002, "neutral": 0.24278078973293304, "contradiction": 0.5987738966941833}, "oriSent": "Vande Mataram is a national song of India, composed by Bankim Chandra Chattopadhyay in 1870s.", "process": "se", "properAnsIDList": 4}, {"question": "What country is Vande Mataram from?", "phrase": "India", "predAns": "Rabindranath Tagore", "predScore": 0.9832151532173157, "MatchScore": {"entailment": 0.1428033858537674, "neutral": 0.7121930122375488, "contradiction": 0.14500358700752258}, "oriSent": "Vande Mataram is a national song of India, composed by Bankim Chandra Chattopadhyay in 1870s.", "process": "se", "properAnsIDList": 8}, {"question": "Who composed Vande Mataram?", "phrase": "Bankim Chandra Chattopadhyay", "predAns": "Zubeen Garg", "predScore": 0.9852145910263062, "MatchScore": {"entailment": 0.007727289106696844, "neutral": 0.00751675758510828, "contradiction": 0.9847559332847595}, "oriSent": "Vande Mataram is a national song of India, composed by Bankim Chandra Chattopadhyay in 1870s.", "process": "se", "properAnsIDList": 5}, {"question": "When was Vande Mataram composed?", "phrase": "1870s", "predAns": "Rabindranath Tagore", "predScore": 0.9781128764152527, "MatchScore": {"entailment": 0.08317534625530243, "neutral": 0.8180546164512634, "contradiction": 0.09877004474401474}, "oriSent": "Vande Mataram is a national song of India, composed by Bankim Chandra Chattopadhyay in 1870s.", "process": "se", "properAnsIDList": 2}, {"question": "When was the song first sung?", "phrase": "first", "predAns": "RabindraNath Tagore", "predScore": 0.9829407334327698, "MatchScore": {"entailment": 0.2742573022842407, "neutral": 0.44147101044654846, "contradiction": 0.2842716574668884}, "oriSent": "It was first sung in the 1896 session of the Indian National Congress.", "process": "se", "properAnsIDList": 8}, {"question": "When was the first time the song was sung?", "phrase": "1896", "predAns": "1896", "predScore": 0.9836297631263733, "MatchScore": {"entailment": 0.9376116394996643, "neutral": 0.04298017919063568, "contradiction": 0.019408226013183594}, "oriSent": "It was first sung in the 1896 session of the Indian National Congress.", "process": "se", "properAnsIDList": 5}, {"question": "What Congress was the first time the song was sung?", "phrase": "the Indian National Congress", "predAns": "Rabindranath Tagore", "predScore": 0.9710990190505981, "MatchScore": {"entailment": 0.027571842074394226, "neutral": 0.1567271649837494, "contradiction": 0.8157009482383728}, "oriSent": "It was first sung in the 1896 session of the Indian National Congress.", "process": "se", "properAnsIDList": 2}, {"question": "What nationality was the song?", "phrase": "Indian", "predAns": "Rabindranath Tagore", "predScore": 0.9876523613929749, "MatchScore": {"entailment": 0.09278295934200287, "neutral": 0.8886147737503052, "contradiction": 0.01860223524272442}, "oriSent": "The song became an anthem of the Indian independence movement and is still widely sung in India today.", "process": "se", "properAnsIDList": 4}, {"question": "In what country is the song still popular?", "phrase": "India", "predAns": "Lata Mangeshkar", "predScore": 0.9565885066986084, "MatchScore": {"entailment": 0.11450640112161636, "neutral": 0.7856196165084839, "contradiction": 0.09987401962280273}, "oriSent": "The song became an anthem of the Indian independence movement and is still widely sung in India today.", "process": "se", "properAnsIDList": 2}, {"question": "How is the song still sung in India?", "phrase": "today", "predAns": "Pt. Omkarnath Thakur", "predScore": 0.785042941570282, "MatchScore": {"entailment": 0.14540670812129974, "neutral": 0.3968796730041504, "contradiction": 0.45771360397338867}, "oriSent": "The song became an anthem of the Indian independence movement and is still widely sung in India today.", "process": "se", "properAnsIDList": 4}, {"question": "What song was sang in the 1896 Congress session?", "phrase": "Vande Mataram", "predAns": "Rabindranath Tagore", "predScore": 0.9856117963790894, "MatchScore": {"entailment": 0.18137747049331665, "neutral": 0.2726505398750305, "contradiction": 0.5459719896316528}, "oriSent": "The question of who sang Vande Mataram in the 1896 Congress session has been a topic of debate among historians and music enthusiasts for many years.", "process": "se", "properAnsIDList": 2}, {"question": "In what year did Congress session of the Vande Mataram?", "phrase": "1896", "predAns": "1896", "predScore": 0.9713970422744751, "MatchScore": {"entailment": 0.9376116394996643, "neutral": 0.04298017919063568, "contradiction": 0.019408226013183594}, "oriSent": "The question of who sang Vande Mataram in the 1896 Congress session has been a topic of debate among historians and music enthusiasts for many years.", "process": "se", "properAnsIDList": 6}, {"question": "What session of Congress was Vande Mataram in?", "phrase": "Congress", "predAns": "Indian National Congress", "predScore": 0.702596127986908, "MatchScore": {"entailment": 0.8847544193267822, "neutral": 0.09275200217962265, "contradiction": 0.02249354124069214}, "oriSent": "The question of who sang Vande Mataram in the 1896 Congress session has been a topic of debate among historians and music enthusiasts for many years.", "process": "se", "properAnsIDList": 0}, {"question": "How long has the question of who sang Vande Mataram been a topic of debate among historians and music enthusiasts?", "phrase": "many years", "predAns": "Rabindranath Tagore", "predScore": 0.7926554679870605, "MatchScore": {"entailment": 0.06622461974620819, "neutral": 0.9241898655891418, "contradiction": 0.009585559368133545}, "oriSent": "The question of who sang Vande Mataram in the 1896 Congress session has been a topic of debate among historians and music enthusiasts for many years.", "process": "se", "properAnsIDList": 5}, {"question": "Who sang the song?", "phrase": "Bankim Chandra Chattopadhyay", "predAns": "Rabindranath Tagore", "predScore": 0.9882997274398804, "MatchScore": {"entailment": 0.002814813517034054, "neutral": 0.005474583245813847, "contradiction": 0.9917105436325073}, "oriSent": "While some claim that it was Bankim Chandra Chattopadhyay himself who sang the song, others believe that it was sung by a group of people led by him.", "process": "se", "properAnsIDList": 6}, {"question": "Whose identity was the subject of controversy in the 1896 Congress?", "phrase": "Vande Mataram", "predAns": "Rabindranath Tagore", "predScore": 0.9823587536811829, "MatchScore": {"entailment": 0.18137747049331665, "neutral": 0.2726505398750305, "contradiction": 0.5459719896316528}, "oriSent": "In this article, we will explore the history of Vande Mataram and the controversy surrounding the identity of the singer in the 1896 Congress session.", "process": "se", "properAnsIDList": 0}, {"question": "In what year did the Congress hold a session?", "phrase": "1896", "predAns": "1896", "predScore": 0.9867106080055237, "MatchScore": {"entailment": 0.9376116394996643, "neutral": 0.04298017919063568, "contradiction": 0.019408226013183594}, "oriSent": "In this article, we will explore the history of Vande Mataram and the controversy surrounding the identity of the singer in the 1896 Congress session.", "process": "se", "properAnsIDList": 0}, {"question": "In what session did Mataram's identity become controversial?", "phrase": "Congress", "predAns": "1937", "predScore": 0.6027305126190186, "MatchScore": {"entailment": 0.16080965101718903, "neutral": 0.7334792613983154, "contradiction": 0.10571110248565674}, "oriSent": "In this article, we will explore the history of Vande Mataram and the controversy surrounding the identity of the singer in the 1896 Congress session.", "process": "se", "properAnsIDList": 3}]