[{"question": "What two bands are from the United States?", "phrase": "Local H and For Against", "predAns": "The Last Vegas, and Bob Schneider", "predScore": 0.528065025806427, "MatchScore": {"entailment": 0.020521922037005424, "neutral": 0.06689491122961044, "contradiction": 0.9125831127166748}, "oriSent": "The question of whether Local H and For Against are both from the United States is a matter of debate among music enthusiasts.", "process": "document", "properAnsIDList": "document"}, {"question": "Where are For Against and Local H from?", "phrase": "the United States", "predAns": "Chicago", "predScore": 0.4773348867893219, "MatchScore": {"entailment": 0.5060269832611084, "neutral": 0.4539605677127838, "contradiction": 0.040012434124946594}, "oriSent": "The question of whether Local H and For Against are both from the United States is a matter of debate among music enthusiasts.", "process": "document", "properAnsIDList": "document"}, {"question": "What nationality is Local H?", "phrase": "American", "predAns": "Chicago", "predScore": 0.47615718841552734, "MatchScore": {"entailment": 0.45072710514068604, "neutral": 0.49484285712242126, "contradiction": 0.05443008989095688}, "oriSent": "Local H is an American rock band that was formed in 1996 in the state of Illinois.", "process": "document", "properAnsIDList": "document"}, {"question": "When was Local H formed?", "phrase": "1996", "predAns": "1987", "predScore": 0.9727229475975037, "MatchScore": {"entailment": 0.004430081695318222, "neutral": 0.014978015795350075, "contradiction": 0.9805919528007507}, "oriSent": "Local H is an American rock band that was formed in 1996 in the state of Illinois.", "process": "se", "properAnsIDList": 7}, {"question": "What state was Local H formed in?", "phrase": "Illinois", "predAns": "Illinois", "predScore": 0.9810802936553955, "MatchScore": {"entailment": 0.9442636370658875, "neutral": 0.04605359584093094, "contradiction": 0.009682726114988327}, "oriSent": "Local H is an American rock band that was formed in 1996 in the state of Illinois.", "process": "se", "properAnsIDList": 1}, {"question": "What nationality is For Against?", "phrase": "American", "predAns": "American", "predScore": 0.5489790439605713, "MatchScore": {"entailment": 0.938076376914978, "neutral": 0.05474083870649338, "contradiction": 0.007182795088738203}, "oriSent": "For Against is also an American rock band that was formed in 1986 in the state of California.", "process": "se", "properAnsIDList": 0}, {"question": "When was For Against formed?", "phrase": "1986", "predAns": "1988", "predScore": 0.8921030759811401, "MatchScore": {"entailment": 0.025245318189263344, "neutral": 0.011763911694288254, "contradiction": 0.9629908204078674}, "oriSent": "For Against is also an American rock band that was formed in 1986 in the state of California.", "process": "se", "properAnsIDList": 1}, {"question": "Where was For Against formed?", "phrase": "California", "predAns": "Chicago", "predScore": 0.6632524132728577, "MatchScore": {"entailment": 0.03161932900547981, "neutral": 0.027148526161909103, "contradiction": 0.9412321448326111}, "oriSent": "For Against is also an American rock band that was formed in 1986 in the state of California.", "process": "document", "properAnsIDList": "document"}, {"question": "Where are the two bands from?", "phrase": "the United States", "predAns": "Chicago", "predScore": 0.9431042671203613, "MatchScore": {"entailment": 0.5060269832611084, "neutral": 0.4539605677127838, "contradiction": 0.040012434124946594}, "oriSent": "While both bands are from the United States, they come from different parts of the country and have different musical styles.", "process": "document", "properAnsIDList": "document"}, {"question": "When did the band Living with Lisa gain popularity?", "phrase": "the mid-1990s", "predAns": "first year of the '90s", "predScore": 0.06454169005155563, "MatchScore": {"entailment": 0.05072340369224548, "neutral": 0.1439952403306961, "contradiction": 0.805281400680542}, "oriSent": "They gained popularity in the mid-1990s with their debut album, \"Living with Lisa,\" which featured hit singles such as \"Bound for the Floor\" and \"Hey, Hey.\"", "process": "se", "properAnsIDList": 5}, {"question": "What was the name of the album that featured hit singles such as \"Bound for the Floor\" and \"Hey, Hey\"?", "phrase": "\"Living with Lisa", "predAns": "Chicago", "predScore": 0.4111165404319763, "MatchScore": {"entailment": 0.0033405055291950703, "neutral": 0.980682373046875, "contradiction": 0.015977131202816963}, "oriSent": "They gained popularity in the mid-1990s with their debut album, \"Living with Lisa,\" which featured hit singles such as \"Bound for the Floor\" and \"Hey, Hey.\"", "process": "document", "properAnsIDList": "document"}, {"question": "What was the name of the hit single from Living with Lisa?", "phrase": "Bound for the Floor\"", "predAns": "<unanswerable>", "predScore": 0, "MatchScore": {"entailment": 0.042997654527425766, "neutral": 0.29660215973854065, "contradiction": 0.6604001522064209}, "oriSent": "They gained popularity in the mid-1990s with their debut album, \"Living with Lisa,\" which featured hit singles such as \"Bound for the Floor\" and \"Hey, Hey.\"", "process": "se", "properAnsIDList": 0}, {"question": "What was the name of the hit single from Living with Lisa?", "phrase": "Hey, Hey", "predAns": "<unanswerable>", "predScore": 0, "MatchScore": {"entailment": 0.09721200913190842, "neutral": 0.14207680523395538, "contradiction": 0.7607111930847168}, "oriSent": "They gained popularity in the mid-1990s with their debut album, \"Living with Lisa,\" which featured hit singles such as \"Bound for the Floor\" and \"Hey, Hey.\"", "process": "se", "properAnsIDList": 0}, {"question": "What band is known for their post-punk sound?", "phrase": "For Against", "predAns": "death pose", "predScore": 0.2689904570579529, "MatchScore": {"entailment": 0.21259884536266327, "neutral": 0.4789939224720001, "contradiction": 0.3084072172641754}, "oriSent": "The band has released several albums since then, with their latest being \"Hallelujah! I'm a Bum\" in For Against, on the other hand, is known for their post-punk and new wave sound.", "process": "se", "properAnsIDList": 5}, {"question": "When were the Skeletons formed?", "phrase": "mid-1980s", "predAns": "1990", "predScore": 0.7706113457679749, "MatchScore": {"entailment": 0.1692490577697754, "neutral": 0.08365354686975479, "contradiction": 0.7470974326133728}, "oriSent": "They were formed in the mid-1980s and released their debut album, \"Skeletons,\" in The band gained a cult following in the 1990s with their second album, \"November,\" which featured the hit single \"Sleep.\"", "process": "se", "properAnsIDList": 0}, {"question": "What was the name of the band's debut album?", "phrase": "Skeletons,\" in The band", "predAns": "Black Glitter", "predScore": 0.7416192889213562, "MatchScore": {"entailment": 0.05445269122719765, "neutral": 0.5253274440765381, "contradiction": 0.42021986842155457}, "oriSent": "They were formed in the mid-1980s and released their debut album, \"Skeletons,\" in The band gained a cult following in the 1990s with their second album, \"November,\" which featured the hit single \"Sleep.\"", "process": "document", "properAnsIDList": "document"}, {"question": "When did the band gain a cult following?", "phrase": "the 1990s", "predAns": "their massive hit song", "predScore": 0.37156444787979126, "MatchScore": {"entailment": 0.02958211861550808, "neutral": 0.9539508819580078, "contradiction": 0.016467003151774406}, "oriSent": "They were formed in the mid-1980s and released their debut album, \"Skeletons,\" in The band gained a cult following in the 1990s with their second album, \"November,\" which featured the hit single \"Sleep.\"", "process": "se", "properAnsIDList": 7}, {"question": "What was the name of the band's second album?", "phrase": "second", "predAns": "Black Glitter", "predScore": 0.5740224123001099, "MatchScore": {"entailment": 0.30938902497291565, "neutral": 0.24847419559955597, "contradiction": 0.44213682413101196}, "oriSent": "They were formed in the mid-1980s and released their debut album, \"Skeletons,\" in The band gained a cult following in the 1990s with their second album, \"November,\" which featured the hit single \"Sleep.\"", "process": "document", "properAnsIDList": "document"}, {"question": "What was the name of the band's second album?", "phrase": "November", "predAns": "Black Glitter", "predScore": 0.5740224123001099, "MatchScore": {"entailment": 0.05585344135761261, "neutral": 0.7611188888549805, "contradiction": 0.1830277144908905}, "oriSent": "They were formed in the mid-1980s and released their debut album, \"Skeletons,\" in The band gained a cult following in the 1990s with their second album, \"November,\" which featured the hit single \"Sleep.\"", "process": "document", "properAnsIDList": "document"}, {"question": "What was the name of the hit single on November's album?", "phrase": "\"Sleep", "predAns": "AM-erst", "predScore": 0.22894662618637085, "MatchScore": {"entailment": 0.004545965231955051, "neutral": 0.013213127851486206, "contradiction": 0.9822408556938171}, "oriSent": "They were formed in the mid-1980s and released their debut album, \"Skeletons,\" in The band gained a cult following in the 1990s with their second album, \"November,\" which featured the hit single \"Sleep.\"", "process": "document", "properAnsIDList": "document"}, {"question": "What is the name of the latest album from Local H?", "phrase": "The New Mind Thickness\"", "predAns": "Black Glitter", "predScore": 0.6288274526596069, "MatchScore": {"entailment": 0.03219672664999962, "neutral": 0.26448753476142883, "contradiction": 0.7033156752586365}, "oriSent": "They have released several albums since then, with their latest being \"The New Mind Thickness\" in In conclusion, while both Local H and For Against are from the United States, they come from different parts of the country and have different musical styles.", "process": "document", "properAnsIDList": "document"}, {"question": "Where are Local H and For Against from?", "phrase": "the United States", "predAns": "Chicago", "predScore": 0.657837450504303, "MatchScore": {"entailment": 0.5060269832611084, "neutral": 0.4539605677127838, "contradiction": 0.040012434124946594}, "oriSent": "They have released several albums since then, with their latest being \"The New Mind Thickness\" in In conclusion, while both Local H and For Against are from the United States, they come from different parts of the country and have different musical styles.", "process": "document", "properAnsIDList": "document"}]