[{"question": "What is the name of the popular Christmas song?", "phrase": "\"I'll Be Home for Christmas\"", "predAns": "Bing Crosby", "predScore": 0.9040572643280029, "MatchScore": {"entailment": 0.0019063198706135154, "neutral": 0.9968799352645874, "contradiction": 0.0012138009769842029}, "oriSent": "\"I'll Be Home for Christmas\" is a popular Christmas song that was first released in The song was written by Kim Gannon, Walter Kent, and Buck Ram, who were all accomplished songwriters of their time.", "process": "se", "properAnsIDList": 4}, {"question": "Who wrote the song \"I'll Be Home for Christmas\"?", "phrase": "Kim Gannon", "predAns": "Bing Crosby", "predScore": 0.9657338857650757, "MatchScore": {"entailment": 0.03234735131263733, "neutral": 0.0468396358191967, "contradiction": 0.9208130836486816}, "oriSent": "\"I'll Be Home for Christmas\" is a popular Christmas song that was first released in The song was written by Kim Gannon, Walter Kent, and Buck Ram, who were all accomplished songwriters of their time.", "process": "se", "properAnsIDList": 7}, {"question": "Along with Kim Gannon, Buck Ram and Buck Ram, who wrote the song \"I'll Be Home for Christmas\"?", "phrase": "Walter Kent", "predAns": "Walter Kent", "predScore": 0.9911689758300781, "MatchScore": {"entailment": 0.9364101886749268, "neutral": 0.048250891268253326, "contradiction": 0.015338952653110027}, "oriSent": "\"I'll Be Home for Christmas\" is a popular Christmas song that was first released in The song was written by Kim Gannon, Walter Kent, and Buck Ram, who were all accomplished songwriters of their time.", "process": "se", "properAnsIDList": 4}, {"question": "Along with Kim Gannon and Walter Kent, who wrote the song \"I'll Be Home for Christmas\"?", "phrase": "Buck Ram", "predAns": "Buck Ram", "predScore": 0.9836128950119019, "MatchScore": {"entailment": 0.9204854965209961, "neutral": 0.060678839683532715, "contradiction": 0.018835628405213356}, "oriSent": "\"I'll Be Home for Christmas\" is a popular Christmas song that was first released in The song was written by Kim Gannon, Walter Kent, and Buck Ram, who were all accomplished songwriters of their time.", "process": "se", "properAnsIDList": 7}, {"question": "Who was a prolific songwriter?", "phrase": "Kim Gannon", "predAns": "Sam \"Buck\" Ram", "predScore": 0.9210628867149353, "MatchScore": {"entailment": 0.012631679885089397, "neutral": 0.008588354103267193, "contradiction": 0.9787800312042236}, "oriSent": "Kim Gannon was a prolific songwriter who wrote many popular songs during his career.", "process": "se", "properAnsIDList": 5}, {"question": "When was he born?", "phrase": "1900", "predAns": "1900", "predScore": 0.33046087622642517, "MatchScore": {"entailment": 0.9296321272850037, "neutral": 0.05404233559966087, "contradiction": 0.016325559467077255}, "oriSent": "He was born in 1900 in New York City and began his career in the music industry as a pianist and arranger.", "process": "se", "properAnsIDList": 8}, {"question": "Where was he born?", "phrase": "New York City", "predAns": "Sam \"Buck\" Ram", "predScore": 0.4995441734790802, "MatchScore": {"entailment": 0.13163699209690094, "neutral": 0.43029311299324036, "contradiction": 0.4380699396133423}, "oriSent": "He was born in 1900 in New York City and began his career in the music industry as a pianist and arranger.", "process": "se", "properAnsIDList": 9}, {"question": "Who wrote the lyrics for \"I'll Be Home for Christmas\"?", "phrase": "Gannon", "predAns": "Bing Crosby", "predScore": 0.9568617343902588, "MatchScore": {"entailment": 0.10114458948373795, "neutral": 0.0835292786359787, "contradiction": 0.8153260946273804}, "oriSent": "Gannon wrote the lyrics for \"I'll Be Home for Christmas\" and is credited with creating the song's emotional and heartfelt tone.", "process": "se", "properAnsIDList": 9}, {"question": "What song did Gannon write?", "phrase": "\"I'll Be Home for Christmas\"", "predAns": "J. Kimball", "predScore": 0.24435965716838837, "MatchScore": {"entailment": 0.0022462080232799053, "neutral": 0.9939510822296143, "contradiction": 0.003802716266363859}, "oriSent": "Gannon wrote the lyrics for \"I'll Be Home for Christmas\" and is credited with creating the song's emotional and heartfelt tone.", "process": "se", "properAnsIDList": 4}, {"question": "Who wrote \"I'll Be Home for Christmas\"?", "phrase": "Walter Kent", "predAns": "Bing Crosby", "predScore": 0.9506747722625732, "MatchScore": {"entailment": 0.012678434140980244, "neutral": 0.012519486248493195, "contradiction": 0.9748020172119141}, "oriSent": "Walter Kent was another accomplished songwriter who contributed to the creation of \"I'll Be Home for Christmas.\"", "process": "se", "properAnsIDList": 7}, {"question": "What song did Walter Kent contribute to?", "phrase": "\"I'll Be Home for Christmas", "predAns": "Kim Gannon", "predScore": 0.714962899684906, "MatchScore": {"entailment": 0.0028974951710551977, "neutral": 0.9940721392631531, "contradiction": 0.003030323190614581}, "oriSent": "Walter Kent was another accomplished songwriter who contributed to the creation of \"I'll Be Home for Christmas.\"", "process": "se", "properAnsIDList": 5}, {"question": "When was he born?", "phrase": "1911", "predAns": "1900", "predScore": 0.33046087622642517, "MatchScore": {"entailment": 0.011423563584685326, "neutral": 0.03837785869836807, "contradiction": 0.9501985907554626}, "oriSent": "He was born in 1911 in New York City and began his career in the music industry as a pianist and composer.", "process": "se", "properAnsIDList": 8}, {"question": "Where was he born?", "phrase": "New York City", "predAns": "Sam \"Buck\" Ram", "predScore": 0.4995441734790802, "MatchScore": {"entailment": 0.13163699209690094, "neutral": 0.43029311299324036, "contradiction": 0.4380699396133423}, "oriSent": "He was born in 1911 in New York City and began his career in the music industry as a pianist and composer.", "process": "se", "properAnsIDList": 9}, {"question": "Who wrote the music for the song?", "phrase": "Kent", "predAns": "Bing Crosby", "predScore": 0.959984302520752, "MatchScore": {"entailment": 0.10240165144205093, "neutral": 0.11278624087572098, "contradiction": 0.7848120331764221}, "oriSent": "Kent wrote the music for the song and is credited with creating the song's upbeat and cheerful melody.", "process": "se", "properAnsIDList": 9}, {"question": "Who was the name of the songwriter and record producer?", "phrase": "Buck Ram", "predAns": "Sam \"Buck\" Ram", "predScore": 0.9404060244560242, "MatchScore": {"entailment": 0.866118311882019, "neutral": 0.09177939593791962, "contradiction": 0.04210232198238373}, "oriSent": "Buck Ram was a songwriter and record producer who was born in 1900 in Ukraine.", "process": "se", "properAnsIDList": 3}, {"question": "When was Buck Ram born?", "phrase": "1900", "predAns": "November 21, 1907", "predScore": 0.6234942078590393, "MatchScore": {"entailment": 0.16518133878707886, "neutral": 0.04815949872136116, "contradiction": 0.7866591811180115}, "oriSent": "Buck Ram was a songwriter and record producer who was born in 1900 in Ukraine.", "process": "se", "properAnsIDList": 1}, {"question": "Where was Buck Ram born?", "phrase": "Ukraine", "predAns": "1907", "predScore": 0.49299588799476624, "MatchScore": {"entailment": 0.07739105075597763, "neutral": 0.7654852867126465, "contradiction": 0.1571236550807953}, "oriSent": "Buck Ram was a songwriter and record producer who was born in 1900 in Ukraine.", "process": "se", "properAnsIDList": 1}, {"question": "Where did he move to as a child?", "phrase": "the United States", "predAns": "<unanswerable>", "predScore": 0, "MatchScore": {"entailment": 0.016994666308164597, "neutral": 0.9209339022636414, "contradiction": 0.06207149475812912}, "oriSent": "He immigrated to the United States as a child and began his career in the music industry as a pianist and arranger.", "process": "se", "properAnsIDList": 0}, {"question": "Who was responsible for creating the unique sound of the song?", "phrase": "Ram", "predAns": "Sam \"Buck\" Ram", "predScore": 0.9532557725906372, "MatchScore": {"entailment": 0.736185610294342, "neutral": 0.14459116756916046, "contradiction": 0.1192232072353363}, "oriSent": "Ram was responsible for arranging the song and is credited with creating the song's unique sound.", "process": "se", "properAnsIDList": 4}, {"question": "What song was first recorded by The King's Men?", "phrase": "\"I'll Be Home for Christmas\"", "predAns": "Bing Crosby", "predScore": 0.8343017101287842, "MatchScore": {"entailment": 0.0019063198706135154, "neutral": 0.9968799352645874, "contradiction": 0.0012138009769842029}, "oriSent": "\"I'll Be Home for Christmas\" was first recorded by the singing group The King's Men in The song became an instant hit and has since been covered by numerous artists, including Bing Crosby, Dean Martin, and Michael Bubl\u00e9.", "process": "se", "properAnsIDList": 9}, {"question": "What group first recorded the song \"I'll Be Home for Christmas\"?", "phrase": "The King's Men", "predAns": "Josh Groban", "predScore": 0.9711029529571533, "MatchScore": {"entailment": 0.06688790768384933, "neutral": 0.1717391014099121, "contradiction": 0.7613729238510132}, "oriSent": "\"I'll Be Home for Christmas\" was first recorded by the singing group The King's Men in The song became an instant hit and has since been covered by numerous artists, including Bing Crosby, Dean Martin, and Michael Bubl\u00e9.", "process": "se", "properAnsIDList": 9}, {"question": "Along with Dean Martin and Michael Bubl\u00e9, who has covered the song \"I'll Be Home for Christmas\"?", "phrase": "Bing Crosby", "predAns": "Josh Groban", "predScore": 0.9230479598045349, "MatchScore": {"entailment": 0.0028810128569602966, "neutral": 0.004660428501665592, "contradiction": 0.9924585223197937}, "oriSent": "\"I'll Be Home for Christmas\" was first recorded by the singing group The King's Men in The song became an instant hit and has since been covered by numerous artists, including Bing Crosby, Dean Martin, and Michael Bubl\u00e9.", "process": "se", "properAnsIDList": 4}, {"question": "Along with Bing Crosby and Michael Bubl\u00e9, who has covered the song \"I'll Be Home for Christmas\"?", "phrase": "Dean Martin", "predAns": "Kim Gannon", "predScore": 0.7931687235832214, "MatchScore": {"entailment": 0.019739674404263496, "neutral": 0.011773291975259781, "contradiction": 0.9684870839118958}, "oriSent": "\"I'll Be Home for Christmas\" was first recorded by the singing group The King's Men in The song became an instant hit and has since been covered by numerous artists, including Bing Crosby, Dean Martin, and Michael Bubl\u00e9.", "process": "se", "properAnsIDList": 7}, {"question": "Along with Bing Crosby and Dean Martin, who has covered the song \"I'll Be Home for Christmas\"?", "phrase": "Michael Bubl\u00e9", "predAns": "Scarlett Johansson", "predScore": 0.9130213856697083, "MatchScore": {"entailment": 0.0036859516985714436, "neutral": 0.003260596189647913, "contradiction": 0.9930534958839417}, "oriSent": "\"I'll Be Home for Christmas\" was first recorded by the singing group The King's Men in The song became an instant hit and has since been covered by numerous artists, including Bing Crosby, Dean Martin, and Michael Bubl\u00e9.", "process": "se", "properAnsIDList": 6}, {"question": "What is the name of the classic song written by three talented songwriters?", "phrase": "\"I'll Be Home for Christmas\"", "predAns": "Kim Gannon and Walter Kent", "predScore": 0.8583370447158813, "MatchScore": {"entailment": 0.006062461994588375, "neutral": 0.9341984391212463, "contradiction": 0.0597391277551651}, "oriSent": "In conclusion, \"I'll Be Home for Christmas\" is a timeless Christmas classic that was written by three talented songwriters, Kim Gannon, Walter Kent, and Buck Ram.", "process": "se", "properAnsIDList": 7}, {"question": "How many talented songwriters wrote \"I'll Be Home for Christmas\"?", "phrase": "three", "predAns": "Whitney Houston", "predScore": 0.9503241181373596, "MatchScore": {"entailment": 0.49928760528564453, "neutral": 0.21319428086280823, "contradiction": 0.28751808404922485}, "oriSent": "In conclusion, \"I'll Be Home for Christmas\" is a timeless Christmas classic that was written by three talented songwriters, Kim Gannon, Walter Kent, and Buck Ram.", "process": "se", "properAnsIDList": 1}, {"question": "Who wrote \"I'll Be Home for Christmas\"?", "phrase": "Kim Gannon", "predAns": "Bing Crosby", "predScore": 0.9506747722625732, "MatchScore": {"entailment": 0.03234735131263733, "neutral": 0.0468396358191967, "contradiction": 0.9208130836486816}, "oriSent": "In conclusion, \"I'll Be Home for Christmas\" is a timeless Christmas classic that was written by three talented songwriters, Kim Gannon, Walter Kent, and Buck Ram.", "process": "se", "properAnsIDList": 7}, {"question": "Along with Kim Gannon and Buck Ram, who wrote \"I'll Be Home for Christmas\"?", "phrase": "Walter Kent", "predAns": "Walter Kent", "predScore": 0.9916021823883057, "MatchScore": {"entailment": 0.9364101886749268, "neutral": 0.048250891268253326, "contradiction": 0.015338952653110027}, "oriSent": "In conclusion, \"I'll Be Home for Christmas\" is a timeless Christmas classic that was written by three talented songwriters, Kim Gannon, Walter Kent, and Buck Ram.", "process": "se", "properAnsIDList": 6}, {"question": "Along with Kim Gannon and Walter Kent, who wrote \"I'll Be Home for Christmas\"?", "phrase": "Buck Ram", "predAns": "Buck Ram", "predScore": 0.9836045503616333, "MatchScore": {"entailment": 0.9204854965209961, "neutral": 0.060678839683532715, "contradiction": 0.018835628405213356}, "oriSent": "In conclusion, \"I'll Be Home for Christmas\" is a timeless Christmas classic that was written by three talented songwriters, Kim Gannon, Walter Kent, and Buck Ram.", "process": "se", "properAnsIDList": 7}]