[{"question": "How many countries have field hockey as their national sport?", "phrase": "one", "predAns": "2", "predScore": 0.6736236810684204, "MatchScore": {"entailment": 0.01651645079255104, "neutral": 0.009259995073080063, "contradiction": 0.9742234945297241}, "oriSent": "However, there is only one country that has field hockey as its national sport, and that country is Pakistan.", "process": "se", "properAnsIDList": 6}, {"question": "What is the only country that has field hockey as its national sport?", "phrase": "Pakistan", "predAns": "polo, and squash", "predScore": 0.24675244092941284, "MatchScore": {"entailment": 0.0292302668094635, "neutral": 0.5355142951011658, "contradiction": 0.4352554380893707}, "oriSent": "However, there is only one country that has field hockey as its national sport, and that country is Pakistan.", "process": "se", "properAnsIDList": 1}, {"question": "Where is field hockey played?", "phrase": "Pakistan", "predAns": "cricket", "predScore": 0.7686119079589844, "MatchScore": {"entailment": 0.01489948108792305, "neutral": 0.9212850332260132, "contradiction": 0.06381544470787048}, "oriSent": "Field hockey has a long and storied history in Pakistan, with the sport being played there since the early 20th century.", "process": "se", "properAnsIDList": 3}, {"question": "When was field hockey first played in Pakistan?", "phrase": "the early 20th century", "predAns": "1948", "predScore": 0.970024824142456, "MatchScore": {"entailment": 0.3168703019618988, "neutral": 0.07508338242769241, "contradiction": 0.6080464124679565}, "oriSent": "Field hockey has a long and storied history in Pakistan, with the sport being played there since the early 20th century.", "process": "se", "properAnsIDList": 0}, {"question": "When was the Pakistan Hockey Federation established?", "phrase": "1958", "predAns": "Field hockey", "predScore": 0.9460731744766235, "MatchScore": {"entailment": 0.06768637150526047, "neutral": 0.8899016380310059, "contradiction": 0.04241195693612099}, "oriSent": "In 1958, the Pakistan Hockey Federation was established, and since then, the country has dominated the sport on the international stage.", "process": "se", "properAnsIDList": 6}, {"question": "What was established in 1958?", "phrase": "the Pakistan Hockey Federation", "predAns": "Hockey", "predScore": 0.5449826121330261, "MatchScore": {"entailment": 0.006380925886332989, "neutral": 0.9860208630561829, "contradiction": 0.00759820407256484}, "oriSent": "In 1958, the Pakistan Hockey Federation was established, and since then, the country has dominated the sport on the international stage.", "process": "se", "properAnsIDList": 6}, {"question": "Which country has won the Olympic gold medal three times?", "phrase": "Pakistan", "predAns": "field hockey", "predScore": 0.9831356406211853, "MatchScore": {"entailment": 0.028685126453638077, "neutral": 0.7531381845474243, "contradiction": 0.2181766778230667}, "oriSent": "Pakistan has won the Olympic gold medal in field hockey three times, and has also won the World Cup twice.", "process": "se", "properAnsIDList": 9}, {"question": "What type of gold medal has Pakistan won three times?", "phrase": "Olympic", "predAns": "Champions Trophy", "predScore": 0.965615451335907, "MatchScore": {"entailment": 0.16961675882339478, "neutral": 0.3752609193325043, "contradiction": 0.4551222622394562}, "oriSent": "Pakistan has won the Olympic gold medal in field hockey three times, and has also won the World Cup twice.", "process": "se", "properAnsIDList": 5}, {"question": "How many times has Pakistan won the Olympic gold medal in field hockey?", "phrase": "three", "predAns": "three", "predScore": 0.8454408645629883, "MatchScore": {"entailment": 0.9359899759292603, "neutral": 0.04854147136211395, "contradiction": 0.015468575060367584}, "oriSent": "Pakistan has won the Olympic gold medal in field hockey three times, and has also won the World Cup twice.", "process": "se", "properAnsIDList": 0}, {"question": "What competition has Pakistan won twice?", "phrase": "the World Cup", "predAns": "field hockey", "predScore": 0.6037903428077698, "MatchScore": {"entailment": 0.008436349220573902, "neutral": 0.9863144159317017, "contradiction": 0.00524919293820858}, "oriSent": "Pakistan has won the Olympic gold medal in field hockey three times, and has also won the World Cup twice.", "process": "se", "properAnsIDList": 1}, {"question": "How many halves is field hockey typically played in?", "phrase": "two", "predAns": "2", "predScore": 0.6673762798309326, "MatchScore": {"entailment": 0.9337759613990784, "neutral": 0.052159152925014496, "contradiction": 0.01406481210142374}, "oriSent": "Field hockey is typically played on a grass field, and the game is divided into two halves of 35 minutes each.", "process": "se", "properAnsIDList": 2}, {"question": "How long are the two halves of field hockey?", "phrase": "35 minutes", "predAns": "35 minutes", "predScore": 0.8171975612640381, "MatchScore": {"entailment": 0.9392754435539246, "neutral": 0.042832985520362854, "contradiction": 0.017891554161906242}, "oriSent": "Field hockey is typically played on a grass field, and the game is divided into two halves of 35 minutes each.", "process": "se", "properAnsIDList": 4}, {"question": "What country is field hockey popular in?", "phrase": "Pakistan", "predAns": "India", "predScore": 0.8216946125030518, "MatchScore": {"entailment": 0.009288324043154716, "neutral": 0.022464388981461525, "contradiction": 0.9682472944259644}, "oriSent": "In addition to Pakistan, field hockey is also popular in other countries such as India, Canada, and the United States.", "process": "se", "properAnsIDList": 4}, {"question": "Along with Canada and the United States, what other country has field hockey?", "phrase": "India", "predAns": "India", "predScore": 0.6426498293876648, "MatchScore": {"entailment": 0.8968167901039124, "neutral": 0.08479239791631699, "contradiction": 0.01839076541364193}, "oriSent": "In addition to Pakistan, field hockey is also popular in other countries such as India, Canada, and the United States.", "process": "se", "properAnsIDList": 3}, {"question": "Along with India and the United States, what other country is field hockey popular in?", "phrase": "Canada", "predAns": "polo", "predScore": 0.29607826471328735, "MatchScore": {"entailment": 0.02673751674592495, "neutral": 0.42790237069129944, "contradiction": 0.5453601479530334}, "oriSent": "In addition to Pakistan, field hockey is also popular in other countries such as India, Canada, and the United States.", "process": "se", "properAnsIDList": 1}, {"question": "Along with India, Canada and Pakistan, what other country is field hockey popular in?", "phrase": "the United States", "predAns": "polo", "predScore": 0.3130699694156647, "MatchScore": {"entailment": 0.163225919008255, "neutral": 0.34776169061660767, "contradiction": 0.48901236057281494}, "oriSent": "In addition to Pakistan, field hockey is also popular in other countries such as India, Canada, and the United States.", "process": "se", "properAnsIDList": 1}, {"question": "What country has a rich history and tradition in field hockey?", "phrase": "Pakistan", "predAns": "Field hockey", "predScore": 0.6571470499038696, "MatchScore": {"entailment": 0.03262151777744293, "neutral": 0.738694965839386, "contradiction": 0.2286835014820099}, "oriSent": "In conclusion, field hockey is the national sport of Pakistan, a country with a rich history and tradition in the sport.", "process": "se", "properAnsIDList": 1}, {"question": "What country has a special relationship with field hockey?", "phrase": "Pakistan", "predAns": "Canada", "predScore": 0.9181013703346252, "MatchScore": {"entailment": 0.014478882774710655, "neutral": 0.022048400714993477, "contradiction": 0.9634727835655212}, "oriSent": "While field hockey is also popular in other countries, it is important to recognize that Pakistan has a unique and special relationship with the sport, and that it is an integral part of the country's cultural identity.", "process": "se", "properAnsIDList": 4}]