{"Usage_title": 0, "Usage_extraction": 0, "generatedTitle": "what was the role of the overseer in roman agriculture", "extractFactDictList": [{"question": "What type of farms did slave overseers play a vital role in?", "phrase": "Roman", "sentence": "Despite these challenges, the slave foreman or overseer played a vital role in the operation of Roman farms, and their contributions were essential to the success of these enterprises."}, {"question": "What type of farm did the slave overseer work for?", "phrase": "Roman", "sentence": "In this essay, we will explore the role of the slave foreman or overseer on a Roman farm in greater detail, including their responsibilities, their training, and the challenges they faced."}]}