[{"question": "Where is early voting an option for voters?", "phrase": "the United States", "predAns": "public election", "predScore": 0.5077466368675232, "MatchScore": {"entailment": 0.023398632183670998, "neutral": 0.9524389505386353, "contradiction": 0.02416239120066166}, "oriSent": "Early voting, also known as absentee voting, has been an option for voters in the United States for over a century.", "process": "se", "properAnsIDList": 0}, {"question": "How long has early voting been an option for voters in the US?", "phrase": "over a century", "predAns": "before Election Day", "predScore": 0.31105732917785645, "MatchScore": {"entailment": 0.07478851824998856, "neutral": 0.23336248099803925, "contradiction": 0.6918489933013916}, "oriSent": "Early voting, also known as absentee voting, has been an option for voters in the United States for over a century.", "process": "se", "properAnsIDList": 9}, {"question": "In what country is early voting still a complex issue?", "phrase": "US", "predAns": "<unanswerable>", "predScore": 0, "MatchScore": {"entailment": 0.057125695049762726, "neutral": 0.8559113144874573, "contradiction": 0.08696296066045761}, "oriSent": "However, the history and development of early voting in the US are complex and have evolved over time.", "process": "se", "properAnsIDList": 0}, {"question": "In what country did early voting begin?", "phrase": "US", "predAns": "Ancient Greece", "predScore": 0.38843414187431335, "MatchScore": {"entailment": 0.022675646468997, "neutral": 0.03225349634885788, "contradiction": 0.9450708627700806}, "oriSent": "This article will provide a comprehensive overview of when early voting started in the US, the different types of early voting, and the key milestones in the history of early voting in the country.", "process": "se", "properAnsIDList": 2}, {"question": "Where is Early Voting History?", "phrase": "US", "predAns": "<unanswerable>", "predScore": 0, "MatchScore": {"entailment": 0.057125695049762726, "neutral": 0.8559113144874573, "contradiction": 0.08696296066045761}, "oriSent": "Early Voting History in the US:", "process": "se", "properAnsIDList": 0}, {"question": "What was California's record for early voting?", "phrase": "first", "predAns": "Nov. 3", "predScore": 0.8464197516441345, "MatchScore": {"entailment": 0.13823090493679047, "neutral": 0.5011132955551147, "contradiction": 0.3606557548046112}, "oriSent": "The first state to introduce early voting was California in 1929, when it allowed voters to cast their ballots before election day.", "process": "se", "properAnsIDList": 4}, {"question": "What state was the first to allow early voting?", "phrase": "California", "predAns": "Oct. 20", "predScore": 0.3558550179004669, "MatchScore": {"entailment": 0.06527866423130035, "neutral": 0.832182765007019, "contradiction": 0.10253855586051941}, "oriSent": "The first state to introduce early voting was California in 1929, when it allowed voters to cast their ballots before election day.", "process": "se", "properAnsIDList": 7}, {"question": "When was California the first state to allow early voting?", "phrase": "1929", "predAns": "<unanswerable>", "predScore": 0, "MatchScore": {"entailment": 0.005417472217231989, "neutral": 0.9760172963142395, "contradiction": 0.018565276637673378}, "oriSent": "The first state to introduce early voting was California in 1929, when it allowed voters to cast their ballots before election day.", "process": "se", "properAnsIDList": 0}, {"question": "What day did California allow early voting?", "phrase": "election day", "predAns": "Monday", "predScore": 0.9722767472267151, "MatchScore": {"entailment": 0.025012141093611717, "neutral": 0.935958981513977, "contradiction": 0.03902889043092728}, "oriSent": "The first state to introduce early voting was California in 1929, when it allowed voters to cast their ballots before election day.", "process": "se", "properAnsIDList": 6}, {"question": "When did early voting become widely adopted?", "phrase": "the 1970s", "predAns": "1965", "predScore": 0.2992634177207947, "MatchScore": {"entailment": 0.08032706379890442, "neutral": 0.06761619448661804, "contradiction": 0.8520568013191223}, "oriSent": "However, early voting was not widely adopted across the country until the 1970s, when several states passed laws allowing absentee voting.", "process": "se", "properAnsIDList": 5}, {"question": "When did Colorado introduce no-excuse absentee voting?", "phrase": "1970", "predAns": "November 8", "predScore": 0.44919493794441223, "MatchScore": {"entailment": 0.14457213878631592, "neutral": 0.4187394976615906, "contradiction": 0.4366884231567383}, "oriSent": "In 1970, Colorado became the first state to introduce no-excuse absentee voting, which allowed voters to cast their ballots without having to provide a reason.", "process": "se", "properAnsIDList": 7}, {"question": "What state was the first to introduce no-excuse absentee voting?", "phrase": "Colorado", "predAns": "<unanswerable>", "predScore": 0, "MatchScore": {"entailment": 0.004678747151046991, "neutral": 0.9376727342605591, "contradiction": 0.057648539543151855}, "oriSent": "In 1970, Colorado became the first state to introduce no-excuse absentee voting, which allowed voters to cast their ballots without having to provide a reason.", "process": "se", "properAnsIDList": 0}, {"question": "What state was Colorado in 1970?", "phrase": "first", "predAns": "<unanswerable>", "predScore": 0, "MatchScore": {"entailment": 0.23499469459056854, "neutral": 0.30904296040534973, "contradiction": 0.45596233010292053}, "oriSent": "In 1970, Colorado became the first state to introduce no-excuse absentee voting, which allowed voters to cast their ballots without having to provide a reason.", "process": "se", "properAnsIDList": 0}, {"question": "What state introduced no-excuse absentee voting?", "phrase": "Oregon", "predAns": "<unanswerable>", "predScore": 0, "MatchScore": {"entailment": 0.005779081955552101, "neutral": 0.8897005915641785, "contradiction": 0.104520283639431}, "oriSent": "This was followed by other states such as Oregon, Washington, and Utah, which also introduced no-excuse absentee voting.", "process": "se", "properAnsIDList": 0}, {"question": "Along with Oregon and Utah, what other state introduced no-excuse absentee voting?", "phrase": "Washington", "predAns": "<unanswerable>", "predScore": 0, "MatchScore": {"entailment": 0.06363342702388763, "neutral": 0.6769772171974182, "contradiction": 0.25938937067985535}, "oriSent": "This was followed by other states such as Oregon, Washington, and Utah, which also introduced no-excuse absentee voting.", "process": "se", "properAnsIDList": 0}, {"question": "Along with Oregon, Washington and Washington, what other state introduced no-excuse absentee voting?", "phrase": "Utah", "predAns": "Washington D.C.", "predScore": 0.7281372547149658, "MatchScore": {"entailment": 0.003394500585272908, "neutral": 0.005739487241953611, "contradiction": 0.9908660054206848}, "oriSent": "This was followed by other states such as Oregon, Washington, and Utah, which also introduced no-excuse absentee voting.", "process": "se", "properAnsIDList": 2}, {"question": "When was the National Voter Registration Act passed?", "phrase": "1986", "predAns": "1993", "predScore": 0.9033554196357727, "MatchScore": {"entailment": 0.0029402701184153557, "neutral": 0.0022382428869605064, "contradiction": 0.9948215484619141}, "oriSent": "In 1986, the National Voter Registration Act (NVRA) was passed, which allowed voters to register and vote on the same day.", "process": "se", "properAnsIDList": 5}, {"question": "What is NVRA?", "phrase": "the National Voter Registration Act", "predAns": "1965", "predScore": 0.6053503155708313, "MatchScore": {"entailment": 0.01046967413276434, "neutral": 0.9706594944000244, "contradiction": 0.018870841711759567}, "oriSent": "In 1986, the National Voter Registration Act (NVRA) was passed, which allowed voters to register and vote on the same day.", "process": "se", "properAnsIDList": 6}, {"question": "What is the National Voter Registration Act?", "phrase": "NVRA", "predAns": "Election Day", "predScore": 0.38934266567230225, "MatchScore": {"entailment": 0.19286325573921204, "neutral": 0.32839933037757874, "contradiction": 0.4787374436855316}, "oriSent": "In 1986, the National Voter Registration Act (NVRA) was passed, which allowed voters to register and vote on the same day.", "process": "se", "properAnsIDList": 5}, {"question": "When did the NVRA allow voters to register and vote?", "phrase": "the same day", "predAns": "1965", "predScore": 0.31477391719818115, "MatchScore": {"entailment": 0.035491522401571274, "neutral": 0.8663321137428284, "contradiction": 0.09817633777856827}, "oriSent": "In 1986, the National Voter Registration Act (NVRA) was passed, which allowed voters to register and vote on the same day.", "process": "se", "properAnsIDList": 8}, {"question": "When was the Help America Vote Act passed?", "phrase": "2000", "predAns": "2002", "predScore": 0.9648844599723816, "MatchScore": {"entailment": 0.026500368490815163, "neutral": 0.009586541913449764, "contradiction": 0.963913083076477}, "oriSent": "In 2000, the Help America Vote Act (HAVA) was passed, which provided funding for the modernization of voting systems and the implementation of voter-verified paper trails.", "process": "se", "properAnsIDList": 0}, {"question": "What is the acronym for the Help America Vote Act?", "phrase": "the Help America Vote Act", "predAns": "2002", "predScore": 0.9638766050338745, "MatchScore": {"entailment": 0.015048264525830746, "neutral": 0.9551394581794739, "contradiction": 0.029812199994921684}, "oriSent": "In 2000, the Help America Vote Act (HAVA) was passed, which provided funding for the modernization of voting systems and the implementation of voter-verified paper trails.", "process": "se", "properAnsIDList": 5}, {"question": "What is the Help America Vote Act?", "phrase": "HAVA", "predAns": "2002", "predScore": 0.9744468331336975, "MatchScore": {"entailment": 0.24857653677463531, "neutral": 0.3893834054470062, "contradiction": 0.3620400130748749}, "oriSent": "In 2000, the Help America Vote Act (HAVA) was passed, which provided funding for the modernization of voting systems and the implementation of voter-verified paper trails.", "process": "se", "properAnsIDList": 7}, {"question": "What organization established the Election Assistance Commission?", "phrase": "HAVA", "predAns": "Help America Vote Act of 2002", "predScore": 0.461471825838089, "MatchScore": {"entailment": 0.3462459444999695, "neutral": 0.23321768641471863, "contradiction": 0.4205363988876343}, "oriSent": "HAVA also established the Election Assistance Commission (EAC), which is responsible for overseeing the administration of federal elections.", "process": "se", "properAnsIDList": 4}, {"question": "What is the EAC?", "phrase": "the Election Assistance Commission", "predAns": "U.S. Election Assistance Commission", "predScore": 0.46016383171081543, "MatchScore": {"entailment": 0.8966333866119385, "neutral": 0.0808061733841896, "contradiction": 0.022560425102710724}, "oriSent": "HAVA also established the Election Assistance Commission (EAC), which is responsible for overseeing the administration of federal elections.", "process": "se", "properAnsIDList": 0}, {"question": "What is the acronym for the Election Assistance Commission?", "phrase": "EAC", "predAns": "EAC", "predScore": 0.9658455848693848, "MatchScore": {"entailment": 0.9025582075119019, "neutral": 0.06449698656797409, "contradiction": 0.03294479846954346}, "oriSent": "HAVA also established the Election Assistance Commission (EAC), which is responsible for overseeing the administration of federal elections.", "process": "se", "properAnsIDList": 3}, {"question": "What day can absentee voters cast their ballots?", "phrase": "election day", "predAns": "Election Day", "predScore": 0.9173619151115417, "MatchScore": {"entailment": 0.9578845500946045, "neutral": 0.037501391023397446, "contradiction": 0.004613968543708324}, "oriSent": "Absentee voting: This type of early voting allows voters to cast their ballots by mail or in person before election day.", "process": "se", "properAnsIDList": 1}, {"question": "On what day can voters cast their ballots in person?", "phrase": "election day", "predAns": "Election Day", "predScore": 0.9539477825164795, "MatchScore": {"entailment": 0.9578845500946045, "neutral": 0.037501391023397446, "contradiction": 0.004613968543708324}, "oriSent": "In-person early voting: This type of early voting allows voters to cast their ballots in person at designated polling stations before election day.", "process": "se", "properAnsIDList": 0}]