[{"question": "What is the name of the mosque in Istanbul?", "phrase": "The Laleli Mosque", "predAns": "Sultan of Tlemcen", "predScore": 0.6746832132339478, "MatchScore": {"entailment": 0.06561791151762009, "neutral": 0.17514395713806152, "contradiction": 0.7592381238937378}, "oriSent": "The Laleli Mosque and Esma Sultan Mansion are two historical structures located in Istanbul, Turkey.", "process": "document", "properAnsIDList": "document"}, {"question": "What is the name of the historical structure located in Istanbul?", "phrase": "Esma Sultan Mansion", "predAns": "Sultan of Tlemcen", "predScore": 0.6559780836105347, "MatchScore": {"entailment": 0.09513718634843826, "neutral": 0.5785004496574402, "contradiction": 0.32636234164237976}, "oriSent": "The Laleli Mosque and Esma Sultan Mansion are two historical structures located in Istanbul, Turkey.", "process": "document", "properAnsIDList": "document"}, {"question": "How many historical structures are located in Istanbul?", "phrase": "two", "predAns": "Laleli, Fatih", "predScore": 0.6162105202674866, "MatchScore": {"entailment": 0.7537975907325745, "neutral": 0.13151392340660095, "contradiction": 0.1146884560585022}, "oriSent": "The Laleli Mosque and Esma Sultan Mansion are two historical structures located in Istanbul, Turkey.", "process": "document", "properAnsIDList": "document"}, {"question": "Where are the Laleli Mosque and the Esma Sultan Mansion located?", "phrase": "Istanbul", "predAns": "Algiers", "predScore": 0.365787148475647, "MatchScore": {"entailment": 0.00817448552697897, "neutral": 0.014335851185023785, "contradiction": 0.9774896502494812}, "oriSent": "The Laleli Mosque and Esma Sultan Mansion are two historical structures located in Istanbul, Turkey.", "process": "document", "properAnsIDList": "document"}, {"question": "In what country is the Laleli Mosque located?", "phrase": "Turkey", "predAns": "Turkey", "predScore": 0.803468644618988, "MatchScore": {"entailment": 0.8991638422012329, "neutral": 0.07846327126026154, "contradiction": 0.02237282320857048}, "oriSent": "The Laleli Mosque and Esma Sultan Mansion are two historical structures located in Istanbul, Turkey.", "process": "document", "properAnsIDList": "document"}, {"question": "What is the name of the mosque?", "phrase": "Laleli Mosque:", "predAns": "Sultan of Tlemcen", "predScore": 0.5461574196815491, "MatchScore": {"entailment": 0.022064456716179848, "neutral": 0.07886720448732376, "contradiction": 0.8990683555603027}, "oriSent": "Laleli Mosque:", "process": "document", "properAnsIDList": "document"}, {"question": "What is the Sultan Ahmed Mosque also known as?", "phrase": "The Laleli Mosque", "predAns": "Algiers", "predScore": 0.5346821546554565, "MatchScore": {"entailment": 0.054443083703517914, "neutral": 0.8723209500312805, "contradiction": 0.07323594391345978}, "oriSent": "The Laleli Mosque, also known as the Sultan Ahmed Mosque, is located in the Laleli district of Istanbul.", "process": "document", "properAnsIDList": "document"}, {"question": "What is the Laleli Mosque also known as?", "phrase": "the Sultan Ahmed Mosque", "predAns": "Algiers", "predScore": 0.9064815044403076, "MatchScore": {"entailment": 0.02094009518623352, "neutral": 0.9520302414894104, "contradiction": 0.027029603719711304}, "oriSent": "The Laleli Mosque, also known as the Sultan Ahmed Mosque, is located in the Laleli district of Istanbul.", "process": "document", "properAnsIDList": "document"}, {"question": "What district of Istanbul is the Sultan Ahmed Mosque located in?", "phrase": "Laleli", "predAns": "K\u00fclliye", "predScore": 0.6871445178985596, "MatchScore": {"entailment": 0.13705343008041382, "neutral": 0.06348000466823578, "contradiction": 0.799466609954834}, "oriSent": "The Laleli Mosque, also known as the Sultan Ahmed Mosque, is located in the Laleli district of Istanbul.", "process": "document", "properAnsIDList": "document"}, {"question": "In what city is the Laleli Mosque located?", "phrase": "Istanbul", "predAns": "Algiers", "predScore": 0.9099649786949158, "MatchScore": {"entailment": 0.00817448552697897, "neutral": 0.014335851185023785, "contradiction": 0.9774896502494812}, "oriSent": "The Laleli Mosque, also known as the Sultan Ahmed Mosque, is located in the Laleli district of Istanbul.", "process": "document", "properAnsIDList": "document"}, {"question": "When was the mosque built?", "phrase": "the 16th century", "predAns": "1097", "predScore": 0.7420602440834045, "MatchScore": {"entailment": 0.40060049295425415, "neutral": 0.1904979795217514, "contradiction": 0.40890148282051086}, "oriSent": "The mosque was built in the 16th century during the reign of Sultan Ahmed I and is considered one of the most important examples of Ottoman architecture in the city.", "process": "document", "properAnsIDList": "document"}, {"question": "Who was the ruler of Istanbul?", "phrase": "Sultan Ahmed I", "predAns": "Ahmed I", "predScore": 0.8707399368286133, "MatchScore": {"entailment": 0.1267126500606537, "neutral": 0.7586436867713928, "contradiction": 0.1146436408162117}, "oriSent": "The mosque was built in the 16th century during the reign of Sultan Ahmed I and is considered one of the most important examples of Ottoman architecture in the city.", "process": "document", "properAnsIDList": "document"}, {"question": "How many examples of Ottoman architecture are there in Istanbul?", "phrase": "one", "predAns": "Laleli, Fatih", "predScore": 0.6496362686157227, "MatchScore": {"entailment": 0.27870166301727295, "neutral": 0.09678409993648529, "contradiction": 0.6245142817497253}, "oriSent": "The mosque was built in the 16th century during the reign of Sultan Ahmed I and is considered one of the most important examples of Ottoman architecture in the city.", "process": "document", "properAnsIDList": "document"}, {"question": "What type of architecture is the mosque considered to be?", "phrase": "Ottoman", "predAns": "Almoravid", "predScore": 0.48552635312080383, "MatchScore": {"entailment": 0.04010816290974617, "neutral": 0.04065779969096184, "contradiction": 0.919234037399292}, "oriSent": "The mosque was built in the 16th century during the reign of Sultan Ahmed I and is considered one of the most important examples of Ottoman architecture in the city.", "process": "document", "properAnsIDList": "document"}, {"question": "How many different designs does the mosque have?", "phrase": "more than 200", "predAns": "Algiers", "predScore": 0.7132875919342041, "MatchScore": {"entailment": 0.044940173625946045, "neutral": 0.9327260851860046, "contradiction": 0.022333798930048943}, "oriSent": "The mosque is famous for its intricate tile work, which features more than 200 different designs and patterns.", "process": "document", "properAnsIDList": "document"}, {"question": "What is the name of the mansion?", "phrase": "Esma Sultan", "predAns": "Hagia Sophia", "predScore": 0.13149452209472656, "MatchScore": {"entailment": 0.05607699975371361, "neutral": 0.04495273530483246, "contradiction": 0.8989702463150024}, "oriSent": "Esma Sultan Mansion:", "process": "document", "properAnsIDList": "document"}, {"question": "What is the Esma Han?", "phrase": "The Esma Sultan Mansion", "predAns": "Algiers", "predScore": 0.5233423113822937, "MatchScore": {"entailment": 0.036731086671352386, "neutral": 0.8478335738182068, "contradiction": 0.11543530970811844}, "oriSent": "The Esma Sultan Mansion, also known as the Esma Han, is located in the Emin\u00f6n\u00fc district of Istanbul.", "process": "document", "properAnsIDList": "document"}, {"question": "What is another name for the Esma Sultan Mansion?", "phrase": "the Esma Han", "predAns": "Algiers", "predScore": 0.5011916160583496, "MatchScore": {"entailment": 0.14948952198028564, "neutral": 0.22281602025032043, "contradiction": 0.6276944875717163}, "oriSent": "The Esma Sultan Mansion, also known as the Esma Han, is located in the Emin\u00f6n\u00fc district of Istanbul.", "process": "document", "properAnsIDList": "document"}, {"question": "In what district of Istanbul is the Esma Sultan Mansion located?", "phrase": "Emin\u00f6n\u00fc", "predAns": "Fatih", "predScore": 0.6428743600845337, "MatchScore": {"entailment": 0.10014349967241287, "neutral": 0.057095304131507874, "contradiction": 0.8427611589431763}, "oriSent": "The Esma Sultan Mansion, also known as the Esma Han, is located in the Emin\u00f6n\u00fc district of Istanbul.", "process": "document", "properAnsIDList": "document"}, {"question": "In what city is the Esma Sultan Mansion located?", "phrase": "Istanbul", "predAns": "Algiers", "predScore": 0.6974548101425171, "MatchScore": {"entailment": 0.00817448552697897, "neutral": 0.014335851185023785, "contradiction": 0.9774896502494812}, "oriSent": "The Esma Sultan Mansion, also known as the Esma Han, is located in the Emin\u00f6n\u00fc district of Istanbul.", "process": "document", "properAnsIDList": "document"}, {"question": "When was the mansion built?", "phrase": "the 18th century", "predAns": "1760", "predScore": 0.9581931829452515, "MatchScore": {"entailment": 0.6506550312042236, "neutral": 0.11858242005109787, "contradiction": 0.23076248168945312}, "oriSent": "The mansion was built in the 18th century during the reign of Sultan Abdulhamid I and served as a palace for the sultan's daughter, Esma Sultan.", "process": "se", "properAnsIDList": 3}, {"question": "Who was the ruler of the kingdom?", "phrase": "Sultan Abdulhamid", "predAns": "Ahmed I", "predScore": 0.804393470287323, "MatchScore": {"entailment": 0.0037848467472940683, "neutral": 0.01142672449350357, "contradiction": 0.9847884178161621}, "oriSent": "The mansion was built in the 18th century during the reign of Sultan Abdulhamid I and served as a palace for the sultan's daughter, Esma Sultan.", "process": "document", "properAnsIDList": "document"}, {"question": "Who was the sultan's daughter?", "phrase": "Esma Sultan", "predAns": "Esma Sultan", "predScore": 0.4985283315181732, "MatchScore": {"entailment": 0.9007824063301086, "neutral": 0.06963784247636795, "contradiction": 0.029579728841781616}, "oriSent": "The mansion was built in the 18th century during the reign of Sultan Abdulhamid I and served as a palace for the sultan's daughter, Esma Sultan.", "process": "document", "properAnsIDList": "document"}, {"question": "What is the name of the mosque in the neighborhood?", "phrase": "the Laleli Mosque", "predAns": "Sultan of Tlemcen", "predScore": 0.4881950914859772, "MatchScore": {"entailment": 0.06840205192565918, "neutral": 0.17598441243171692, "contradiction": 0.7556135654449463}, "oriSent": "To determine whether the Laleli Mosque and Esma Sultan Mansion are located in the same neighborhood, we must compare their addresses.", "process": "document", "properAnsIDList": "document"}, {"question": "What is the name of the other property in the same neighborhood?", "phrase": "Esma Sultan Mansion", "predAns": "Hagia Sophia", "predScore": 0.6718147993087769, "MatchScore": {"entailment": 0.048073504120111465, "neutral": 0.0972403734922409, "contradiction": 0.8546860814094543}, "oriSent": "To determine whether the Laleli Mosque and Esma Sultan Mansion are located in the same neighborhood, we must compare their addresses.", "process": "document", "properAnsIDList": "document"}, {"question": "What is the name of the mosque located in Istanbul?", "phrase": "The Laleli Mosque", "predAns": "Sultan of Tlemcen", "predScore": 0.6318148374557495, "MatchScore": {"entailment": 0.06561791151762009, "neutral": 0.17514395713806152, "contradiction": 0.7592381238937378}, "oriSent": "The Laleli Mosque is located at Laleli Caddesi, No: 1, 34110 Fatih, Istanbul, Turkey.", "process": "document", "properAnsIDList": "document"}, {"question": "Where is the Laleli Mosque located?", "phrase": "Laleli Caddesi", "predAns": "Algiers", "predScore": 0.8450261354446411, "MatchScore": {"entailment": 0.15680775046348572, "neutral": 0.38840341567993164, "contradiction": 0.45478886365890503}, "oriSent": "The Laleli Mosque is located at Laleli Caddesi, No: 1, 34110 Fatih, Istanbul, Turkey.", "process": "document", "properAnsIDList": "document"}, {"question": "Where is the Laleli Mosque located?", "phrase": "34110 Fatih", "predAns": "Algiers", "predScore": 0.8450261354446411, "MatchScore": {"entailment": 0.11268728971481323, "neutral": 0.4718264937400818, "contradiction": 0.4154861867427826}, "oriSent": "The Laleli Mosque is located at Laleli Caddesi, No: 1, 34110 Fatih, Istanbul, Turkey.", "process": "document", "properAnsIDList": "document"}, {"question": "Where is the Laleli Mosque located?", "phrase": "Istanbul", "predAns": "Algiers", "predScore": 0.8450261354446411, "MatchScore": {"entailment": 0.00817448552697897, "neutral": 0.014335851185023785, "contradiction": 0.9774896502494812}, "oriSent": "The Laleli Mosque is located at Laleli Caddesi, No: 1, 34110 Fatih, Istanbul, Turkey.", "process": "document", "properAnsIDList": "document"}, {"question": "Where is the Laleli Mosque located?", "phrase": "Turkey", "predAns": "Algiers", "predScore": 0.8450261354446411, "MatchScore": {"entailment": 0.007194120436906815, "neutral": 0.012845072895288467, "contradiction": 0.9799607396125793}, "oriSent": "The Laleli Mosque is located at Laleli Caddesi, No: 1, 34110 Fatih, Istanbul, Turkey.", "process": "document", "properAnsIDList": "document"}, {"question": "What is the name of the mansion located in Istanbul?", "phrase": "The Esma Sultan Mansion", "predAns": "Hagia Sophia", "predScore": 0.4397052824497223, "MatchScore": {"entailment": 0.0355321541428566, "neutral": 0.12755154073238373, "contradiction": 0.8369163274765015}, "oriSent": "The Esma Sultan Mansion is located at Bankalar Caddesi, No: 16, 34110 Emin\u00f6n\u00fc, Istanbul, Turkey.", "process": "document", "properAnsIDList": "document"}, {"question": "Where is the Esma Sultan Mansion located?", "phrase": "Bankalar Caddesi", "predAns": "Bosphorus", "predScore": 0.3618225157260895, "MatchScore": {"entailment": 0.16293247044086456, "neutral": 0.2696758210659027, "contradiction": 0.5673916935920715}, "oriSent": "The Esma Sultan Mansion is located at Bankalar Caddesi, No: 16, 34110 Emin\u00f6n\u00fc, Istanbul, Turkey.", "process": "document", "properAnsIDList": "document"}, {"question": "What is the street address of the Esma Sultan Mansion?", "phrase": "16", "predAns": "Algiers", "predScore": 0.7169106006622314, "MatchScore": {"entailment": 0.2014346420764923, "neutral": 0.6685806512832642, "contradiction": 0.12998472154140472}, "oriSent": "The Esma Sultan Mansion is located at Bankalar Caddesi, No: 16, 34110 Emin\u00f6n\u00fc, Istanbul, Turkey.", "process": "document", "properAnsIDList": "document"}, {"question": "Where is the Esma Sultan Mansion located?", "phrase": "34110 Emin\u00f6n\u00fc", "predAns": "Bosphorus", "predScore": 0.3618225157260895, "MatchScore": {"entailment": 0.11383234709501266, "neutral": 0.41016849875450134, "contradiction": 0.4759991466999054}, "oriSent": "The Esma Sultan Mansion is located at Bankalar Caddesi, No: 16, 34110 Emin\u00f6n\u00fc, Istanbul, Turkey.", "process": "document", "properAnsIDList": "document"}, {"question": "In what city is the Esma Sultan Mansion located?", "phrase": "Istanbul", "predAns": "Algiers", "predScore": 0.6974548101425171, "MatchScore": {"entailment": 0.00817448552697897, "neutral": 0.014335851185023785, "contradiction": 0.9774896502494812}, "oriSent": "The Esma Sultan Mansion is located at Bankalar Caddesi, No: 16, 34110 Emin\u00f6n\u00fc, Istanbul, Turkey.", "process": "document", "properAnsIDList": "document"}, {"question": "In what country is the Esma Sultan Mansion located?", "phrase": "Turkey", "predAns": "Turkey", "predScore": 0.6763028502464294, "MatchScore": {"entailment": 0.8991638422012329, "neutral": 0.07846327126026154, "contradiction": 0.02237282320857048}, "oriSent": "The Esma Sultan Mansion is located at Bankalar Caddesi, No: 16, 34110 Emin\u00f6n\u00fc, Istanbul, Turkey.", "process": "document", "properAnsIDList": "document"}, {"question": "What is the name of the mosque located in different neighborhoods?", "phrase": "the Laleli Mosque", "predAns": "Laleli, Fatih", "predScore": 0.26182234287261963, "MatchScore": {"entailment": 0.08345207571983337, "neutral": 0.6283162832260132, "contradiction": 0.28823164105415344}, "oriSent": "As can be seen from the addresses, the Laleli Mosque and Esma Sultan Mansion are located in different neighborhoods.", "process": "document", "properAnsIDList": "document"}, {"question": "What is the name of the mansion located in different neighborhoods?", "phrase": "Esma Sultan Mansion", "predAns": "Hagia Sophia", "predScore": 0.14896219968795776, "MatchScore": {"entailment": 0.048073504120111465, "neutral": 0.0972403734922409, "contradiction": 0.8546860814094543}, "oriSent": "As can be seen from the addresses, the Laleli Mosque and Esma Sultan Mansion are located in different neighborhoods.", "process": "document", "properAnsIDList": "document"}, {"question": "What is located in the Laleli district?", "phrase": "The Laleli Mosque", "predAns": "Fatih", "predScore": 0.4216462969779968, "MatchScore": {"entailment": 0.09243562072515488, "neutral": 0.2790411114692688, "contradiction": 0.6285233497619629}, "oriSent": "The Laleli Mosque is located in the Laleli district, while the Esma Sultan Mansion is located in the Emin\u00f6n\u00fc", "process": "document", "properAnsIDList": "document"}, {"question": "Where is the Laleli Mosque located?", "phrase": "Laleli", "predAns": "Algiers", "predScore": 0.8450261354446411, "MatchScore": {"entailment": 0.07567595690488815, "neutral": 0.12675318121910095, "contradiction": 0.7975708246231079}, "oriSent": "The Laleli Mosque is located in the Laleli district, while the Esma Sultan Mansion is located in the Emin\u00f6n\u00fc", "process": "document", "properAnsIDList": "document"}, {"question": "What is located in the Emin\u00f6n\u00fc district?", "phrase": "the Esma Sultan Mansion", "predAns": "Hagia Sophia", "predScore": 0.3111620843410492, "MatchScore": {"entailment": 0.05532098934054375, "neutral": 0.24154330790042877, "contradiction": 0.7031357288360596}, "oriSent": "The Laleli Mosque is located in the Laleli district, while the Esma Sultan Mansion is located in the Emin\u00f6n\u00fc", "process": "document", "properAnsIDList": "document"}, {"question": "Where is the Esma Sultan Mansion located?", "phrase": "Emin\u00f6n\u00fc", "predAns": "Bosphorus", "predScore": 0.3618225157260895, "MatchScore": {"entailment": 0.11929528415203094, "neutral": 0.09185140579938889, "contradiction": 0.7888533473014832}, "oriSent": "The Laleli Mosque is located in the Laleli district, while the Esma Sultan Mansion is located in the Emin\u00f6n\u00fc", "process": "document", "properAnsIDList": "document"}]